{"chunk_definitions":[{"chunk_id":"cqf369r0c5a1a","chunk_label":"unnamed-chunk-1","document_id":"61262AD8","expansion_state":1,"options":{"engine":null},"row":17,"row_count":1,"visible":true},{"chunk_id":"cy63tlzjvf1pn","chunk_label":"unnamed-chunk-2","document_id":"61262AD8","expansion_state":0,"options":{"engine":"r","label":"unnamed-chunk-2"},"row":21,"row_count":1,"visible":true},{"chunk_id":"cep3v8txl98vv","chunk_label":"unnamed-chunk-3","document_id":"61262AD8","expansion_state":0,"options":{"engine":null},"row":32,"row_count":1,"visible":true},{"chunk_id":"chm38w8v8swlc","chunk_label":"unnamed-chunk-4","document_id":"61262AD8","expansion_state":0,"options":{"engine":"r","label":"unnamed-chunk-1"},"row":37,"row_count":1,"visible":true},{"chunk_id":"c0awrselcjcns","chunk_label":"unnamed-chunk-5","document_id":"61262AD8","expansion_state":0,"options":{"engine":null},"row":51,"row_count":1,"visible":true},{"chunk_id":"cfut0beg07a0s","chunk_label":"unnamed-chunk-6","document_id":"61262AD8","expansion_state":0,"options":{"engine":null},"row":63,"row_count":1,"visible":true}],"doc_write_time":1540976200}